aipatt/__init__.py
aipatt/config.py
aipatt/main.py
aipatt/__pycache__/__init__.cpython-311.pyc
aipatt/__pycache__/config.cpython-311.pyc
aipatt/__pycache__/main.cpython-311.pyc
aipatt/ai/__init__.py
aipatt/ai/agent.py
aipatt/ai/llm.py
aipatt/ai/tools.py
aipatt/ai/__pycache__/__init__.cpython-311.pyc
aipatt/ai/__pycache__/agent.cpython-311.pyc
aipatt/ai/__pycache__/llm.cpython-311.pyc
aipatt/ai/__pycache__/tools.cpython-311.pyc
aipatt/utils/__init__.py
aipatt/utils/email.py
aipatt/utils/executor.py
aipatt/utils/formatter.py
aipatt/utils/get_info.py
aipatt/utils/google_search.py
aipatt/utils/weather.py
aipatt/utils/youtube.py
aipatt/utils/__pycache__/__init__.cpython-311.pyc
aipatt/utils/__pycache__/email.cpython-311.pyc
aipatt/utils/__pycache__/executor.cpython-311.pyc
aipatt/utils/__pycache__/formatter.cpython-311.pyc
aipatt/utils/__pycache__/get_info.cpython-311.pyc
aipatt/utils/__pycache__/google_search.cpython-311.pyc
aipatt/utils/__pycache__/weather.cpython-311.pyc
aipatt/utils/__pycache__/youtube.cpython-311.pyc
aipatt-1.2.1.dist-info/LICENSE
aipatt-1.2.1.dist-info/METADATA
aipatt-1.2.1.dist-info/WHEEL
aipatt-1.2.1.dist-info/entry_points.txt
aipatt-1.2.1.dist-info/top_level.txt
aipatt-1.2.1.dist-info/RECORD
