Metadata-Version: 2.1
Name: aipatt
Version: 1.2.1
Summary: AIPATT: AI Powered Assistant Tool for Terminals
Author-email: Somesh Sharma <someshs.ce@gmail.com>
Maintainer-email: Somesh Sharma <someshs.ce@gmail.com>
License:                     GNU AFFERO GENERAL PUBLIC LICENSE
Project-URL: Homepage, http://pypi.org/project/aipatt/
Project-URL: Repository, https://github.com/someshsce/aipatt.git
Project-URL: Issues, https://github.com/someshsce/aipatt/issues
Keywords: AI,Terminal,CMD,command,LLM,Powershell,Assistant,Tool
Classifier: Programming Language :: Python :: 3.10
Classifier: Programming Language :: Python :: 3.11
Classifier: Programming Language :: Python :: 3.12
Classifier: Programming Language :: Python :: 3.13
Classifier: Operating System :: OS Independent
Requires-Python: >=3.10
License-File: LICENSE
Requires-Dist: rich
Requires-Dist: click
Requires-Dist: psutil
Requires-Dist: langchain
Requires-Dist: langgraph
Requires-Dist: python-dotenv
Requires-Dist: beautifulsoup4
Requires-Dist: langchain-core
Requires-Dist: langchain-ollama
Requires-Dist: langchain-community
Requires-Dist: pydantic[email,timezone]
Requires-Dist: langchain_google_community
